com/vmware/__init__.py
com/vmware/appliance_client.py
com/vmware/cis_client.py
com/vmware/content_client.py
com/vmware/esx_client.py
com/vmware/oauth2_client.py
com/vmware/snapservice_client.py
com/vmware/vapi_client.py
com/vmware/vcenter_client.py
com/vmware/vstats_client.py
com/vmware/appliance/__init__.py
com/vmware/appliance/access_client.py
com/vmware/appliance/health_client.py
com/vmware/appliance/infraprofile_client.py
com/vmware/appliance/local_accounts_client.py
com/vmware/appliance/localaccounts_client.py
com/vmware/appliance/logging_client.py
com/vmware/appliance/monitoring_client.py
com/vmware/appliance/networking_client.py
com/vmware/appliance/ntp_client.py
com/vmware/appliance/recovery_client.py
com/vmware/appliance/shutdown_client.py
com/vmware/appliance/support_bundle_client.py
com/vmware/appliance/supportbundle_client.py
com/vmware/appliance/system_client.py
com/vmware/appliance/tls_client.py
com/vmware/appliance/update_client.py
com/vmware/appliance/vmon_client.py
com/vmware/appliance/networking/__init__.py
com/vmware/appliance/networking/dns_client.py
com/vmware/appliance/networking/firewall_client.py
com/vmware/appliance/networking/interfaces_client.py
com/vmware/appliance/recovery/__init__.py
com/vmware/appliance/recovery/backup_client.py
com/vmware/appliance/recovery/reconciliation_client.py
com/vmware/appliance/recovery/restore_client.py
com/vmware/appliance/recovery/backup/__init__.py
com/vmware/appliance/recovery/backup/job_client.py
com/vmware/appliance/recovery/backup/system_name_client.py
com/vmware/appliance/system/__init__.py
com/vmware/appliance/system/security_client.py
com/vmware/appliance/system/time_client.py
com/vmware/appliance/tls/__init__.py
com/vmware/appliance/tls/manual_parameters_client.py
com/vmware/appliance/tls/profiles_client.py
com/vmware/appliance/vcenter/__init__.py
com/vmware/appliance/vcenter/settings/__init__.py
com/vmware/appliance/vcenter/settings/v1_client.py
vmware_vcenter-8.0.3.0.dist-info/LICENSE
vmware_vcenter-8.0.3.0.dist-info/METADATA
vmware_vcenter-8.0.3.0.dist-info/WHEEL
vmware_vcenter-8.0.3.0.dist-info/top_level.txt
vmware_vcenter-8.0.3.0.dist-info/RECORD
